{
  "collapse-filter": true,
  "search": "",
  "showTags": false,
  "showAttachments": true,
  "hideUnresolved": true,
  "showOrphans": true,
  "collapse-color-groups": false,
  "colorGroups": [
    {
      "query": "file:README",
      "color": {
        "a": 1,
        "rgb": 15662848
      }
    },
    {
      "query": "file:\"Digital Visual Design Index\"",
      "color": {
        "a": 1,
        "rgb": 16711680
      }
    },
    {
      "query": "file:\"Digital Storytelling Index\"",
      "color": {
        "a": 1,
        "rgb": 16711680
      }
    },
    {
      "query": "file:\"Intro to Programming (Python) Index\"",
      "color": {
        "a": 1,
        "rgb": 16711680
      }
    }
  ],
  "collapse-display": true,
  "showArrow": false,
  "textFadeMultiplier": 0,
  "nodeSizeMultiplier": 1,
  "lineSizeMultiplier": 1,
  "collapse-forces": false,
  "centerStrength": 0.5,
  "repelStrength": 10,
  "linkStrength": 0.5,
  "linkDistance": 250,
  "scale": 0.2871082067971484,
  "close": false
}